colcol/__init__.py
colcol/algorithms.py
colcol/bezier.py
colcol/colcol.py
colcol/convert.py
colcol/scales.py
colcol-0.13.0.dist-info/DESCRIPTION.rst
colcol-0.13.0.dist-info/METADATA
colcol-0.13.0.dist-info/RECORD
colcol-0.13.0.dist-info/WHEEL
colcol-0.13.0.dist-info/metadata.json
colcol-0.13.0.dist-info/top_level.txt
