Metadata-Version: 2.0
Name: colcol
Version: 0.13.0
Summary: A set of scripts to deal with color conversions, color transformations, and generating color scales.
Home-page: https://github.com/mengqvist/colcol
Author: Martin Engqvist
Author-email: martin_engqvist@hotmail.com
License: GPLv3+
Keywords: color colour conversion scale hue lightness gradient RGB HEX tones hues tints shades
Platform: UNKNOWN
Classifier: Development Status :: 3 - Alpha
Classifier: Intended Audience :: Science/Research
Classifier: Topic :: Scientific/Engineering :: Visualization
Classifier: License :: OSI Approved :: GNU General Public License v3 or later (GPLv3+)
Classifier: Programming Language :: Python :: 3 :: Only
Classifier: Programming Language :: Python :: 3
Classifier: Programming Language :: Python :: 3.2
Classifier: Programming Language :: Python :: 3.3
Classifier: Programming Language :: Python :: 3.4
Classifier: Programming Language :: Python :: 3.5
Classifier: Programming Language :: Python :: 3.6
Requires-Python: >=3
Requires-Dist: colorsys
Requires-Dist: tkinter
